phylojunction/__init__.py
phylojunction/__main__.py
phylojunction/calculation/__init__.py
phylojunction/calculation/discrete_sse.py
phylojunction/calculation/discrete_sse.pyi
phylojunction/calculation/math_utils.py
phylojunction/calculation/math_utils.pyi
phylojunction/constant_function/__init__.py
phylojunction/constant_function/ct_function_read_tree.py
phylojunction/data/__init__.py
phylojunction/data/attribute_transition.py
phylojunction/data/sampled_ancestor.py
phylojunction/data/tree.py
phylojunction/data/tree.pyi
phylojunction/distribution/__init__.py
phylojunction/distribution/dn_discrete_sse.py
phylojunction/distribution/dn_discrete_sse.pyi
phylojunction/distribution/dn_parametric.py
phylojunction/distribution/dn_parametric.pyi
phylojunction/functionality/__init__.py
phylojunction/functionality/biogeo.py
phylojunction/functionality/event_series.py
phylojunction/functionality/evol_event.py
phylojunction/functionality/feature_io.py
phylojunction/functionality/stoch_map.py
phylojunction/inference/__init__.py
phylojunction/inference/revbayes/__init__.py
phylojunction/inference/revbayes/rb_dn_parametric.py
phylojunction/inference/revbayes/rb_inference.py
phylojunction/interface/__init__.py
phylojunction/interface/pj_sandbox.py
phylojunction/interface/cmdbox/__init__.py
phylojunction/interface/cmdbox/cmd_parse.py
phylojunction/interface/cmdbox/cmd_parse.pyi
phylojunction/interface/cmdbox/cmd_parse_utils.py
phylojunction/interface/cmdbox/cmd_parse_utils.pyi
phylojunction/interface/grammar/__init__.py
phylojunction/interface/grammar/ct_fn_grammar.py
phylojunction/interface/grammar/ct_fn_treereader_makers.py
phylojunction/interface/grammar/det_fn_discrete_sse_makers.py
phylojunction/interface/grammar/det_fn_discrete_sse_makers.pyi
phylojunction/interface/grammar/det_fn_grammar.py
phylojunction/interface/grammar/det_fn_grammar.pyi
phylojunction/interface/grammar/det_fn_map_attribute.py
phylojunction/interface/grammar/dn_discrete_sse_makers.py
PhyloJunction-0.0.2.dist-info/LICENSE.rst
PhyloJunction-0.0.2.dist-info/METADATA
PhyloJunction-0.0.2.dist-info/WHEEL
PhyloJunction-0.0.2.dist-info/entry_points.txt
PhyloJunction-0.0.2.dist-info/top_level.txt
PhyloJunction-0.0.2.dist-info/RECORD
